baseutils/__init__.py
baseutils/iter.py
baseutils/option.py
baseutils/py.typed
baseutils-0.1.2.dist-info/LICENSE
baseutils-0.1.2.dist-info/METADATA
baseutils-0.1.2.dist-info/WHEEL
baseutils-0.1.2.dist-info/top_level.txt
baseutils-0.1.2.dist-info/RECORD
